<?xml version="1.0" encoding="utf-8" ?>
<Stat Name="bin">
  <Values>
    <Property Tag="Bin Width" Name="binwidth" Value="0"/>
    <Property Tag="Bins" Name="bins" Value="30"/>
    <Property Tag="Center" Name="center" Value="Null"/>
    <Property Tag="Boundary" Name="boundary" Value="Null"/>
  </Values>
  <Properties>
    <Property Tag="Bandwidth" Name="bw" Value="">
      <Options>
        <Option Name="Silverman" Value="nrd0"/>
        <Option Name="Scott" Value="nrd"/>
        <Option Name="Unbiased Cross Validation" Value="ucv"/>
        <Option Name="Biased Cross Validation" Value="bcv"/>
      </Options>
    </Property>
    <Property Tag="Closed" Name="closed" Value="">
      <Options>
        <Option Name="Right" Value="right"/>
        <Option Name="Left" Value="left"/>
      </Options>
    </Property>
  </Properties>
  <Booleans>
    <Property Tag="Pad" Name="pad" Value="FALSE"/>
  </Booleans>
</Stat>